<annotation>
	<folder>images</folder>
	<filename>hard_hat_workers9.jpg</filename>
	<path>/home/pongsakorn/kaggle_ws/safety_helmet_ws/dataset/images/hard_hat_workers9.jpg</path>
	<source>
		<database>Unknown</database>
	</source>
	<size>
		<width>415</width>
		<height>416</height>
		<depth>3</depth>
	</size>
	<segmented>0</segmented>
	<object>
		<name>Safety Helmet</name>
		<pose>Unspecified</pose>
		<truncated>0</truncated>
		<difficult>0</difficult>
		<bndbox>
			<xmin>259</xmin>
			<ymin>73</ymin>
			<xmax>310</xmax>
			<ymax>129</ymax>
		</bndbox>
	</object>
</annotation>